{
  "events": [
    {
      "idEvent": "1580271",
      "idAPIfootball": "877947",
      "strTimestamp": "2022-08-12T20:00:00",
      "strEvent": "Osasuna vs Sevilla",
      "strEventAlternate": "Sevilla @ Osasuna",
      "strFilename": "Spanish La Liga 2022-08-12 Osasuna vs Sevilla",
      "strSport": "Soccer",
      "idLeague": "4335",
      "strLeague": "Spanish La Liga",
      "strLeagueBadge": "https://r2.thesportsdb.com/images/media/league/badge/ja4it51687628717.png",
      "strSeason": "2022-2023",
      "strDescriptionEN": "The new Liga opens on Friday in Pamplona's El Sadar. Coming back from tenth place last season, the hosts of Osasuna host Sevilla, on the hunt with Julen Lopetegui for another Champions League finish.",
      "strHomeTeam": "Osasuna",
      "strAwayTeam": "Sevilla",
      "intHomeScore": "2",
      "intRound": "1",
      "intAwayScore": "1",
      "intSpectators": null,
      "strOfficial": "",
      "dateEvent": "2022-08-12",
      "dateEventLocal": "2022-08-12",
      "strTime": "19:00:00",
      "strTimeLocal": "21:00:00",
      "strGroup": null,
      "idHomeTeam": "133730",
      "strHomeTeamBadge": null,
      "idAwayTeam": "133735",
      "strAwayTeamBadge": null,
      "intScore": null,
      "intScoreVotes": null,
      "strResult": "",
      "idVenue": "19060",
      "strVenue": "Estadio El Sadar",
      "strCountry": "Spain",
      "strCity": "",
      "strPoster": "",
      "strSquare": "https://r2.thesportsdb.com/images/media/event/square/7cklea1661600195.jpg",
      "strFanart": null,
      "strThumb": "https://r2.thesportsdb.com/images/media/event/thumb/xr4fb91661596856.jpg",
      "strBanner": "",
      "strMap": null,
      "strTweet1": "",
      "strVideo": "https://www.youtube.com/watch?v=A3KtmXU9tZc",
      "strStatus": "Match Finished",
      "strPostponed": "no",
      "strLocked": "unlocked"
    },
    {
      "idEvent": "1580267",
      "idAPIfootball": "877943",
      "strTimestamp": "2022-08-13T20:00:00",
      "strEvent": "Barcelona vs Vallecano",
      "strEventAlternate": "Vallecano @ Barcelona",
      "strFilename": "Spanish La Liga 2022-08-13 Barcelona vs Vallecano",
      "strSport": "Soccer",
      "idLeague": "4335",
      "strLeague": "Spanish La Liga",
      "strLeagueBadge": "https://r2.thesportsdb.com/images/media/league/badge/ja4it51687628717.png",
      "strSeason": "2022-2023",
      "strDescriptionEN": "Barcelona makes its debut in this league championship against a rival that is traditionally good at it, Rayo, but that on its last visit to the Camp Nou attacked the Barça fiefdom. It was Rayista's second victory as a visitor against Barça. Xavi's team has been reinforced very well this season with Raphinha, Lewandowski, Christensen...",
      "strHomeTeam": "Barcelona",
      "strAwayTeam": "Vallecano",
      "intHomeScore": "0",
      "intRound": "1",
      "intAwayScore": "0",
      "intSpectators": null,
      "strOfficial": "",
      "dateEvent": "2022-08-13",
      "dateEventLocal": "2022-08-13",
      "strTime": "19:00:00",
      "strTimeLocal": "21:00:00",
      "strGroup": null,
      "idHomeTeam": "133739",
      "strHomeTeamBadge": null,
      "idAwayTeam": "133728",
      "strAwayTeamBadge": null,
      "intScore": null,
      "intScoreVotes": null,
      "strResult": "",
      "idVenue": "16437",
      "strVenue": "Spotify Camp Nou",
      "strCountry": "Spain",
      "strCity": "",
      "strPoster": "",
      "strSquare": "https://r2.thesportsdb.com/images/media/event/square/lm2sa71661600193.jpg",
      "strFanart": null,
      "strThumb": "https://r2.thesportsdb.com/images/media/event/thumb/3kk3h11661596854.jpg",
      "strBanner": "",
      "strMap": null,
      "strTweet1": "",
      "strVideo": "https://www.youtube.com/watch?v=oQEjM-JJ0yA",
      "strStatus": "Match Finished",
      "strPostponed": "no",
      "strLocked": "unlocked"
    },
    {
      "idEvent": "1580269",
      "idAPIfootball": "877945",
      "strTimestamp": "2022-08-13T16:00:00",
      "strEvent": "Celta Vigo vs Espanol",
      "strEventAlternate": "Espanol @ Celta Vigo",
      "strFilename": "Spanish La Liga 2022-08-13 Celta Vigo vs Espanol",
      "strSport": "Soccer",
      "idLeague": "4335",
      "strLeague": "Spanish La Liga",
      "strLeagueBadge": "https://r2.thesportsdb.com/images/media/league/badge/ja4it51687628717.png",
      "strSeason": "2022-2023",
      "strDescriptionEN": "Celta de Vigo kick off LaLiga in front of their fans, who are eager to see what Eduardo Coudet can do for his team in this third term for the Argentine in Balaídos. Their rival, RCD Espanyol, opens the season as a visitor and with the illusion that a new coach, Diego Martínez, always arouses.",
      "strHomeTeam": "Celta Vigo",
      "strAwayTeam": "Espanol",
      "intHomeScore": "2",
      "intRound": "1",
      "intAwayScore": "2",
      "intSpectators": null,
      "strOfficial": "",
      "dateEvent": "2022-08-13",
      "dateEventLocal": "2022-08-13",
      "strTime": "15:00:00",
      "strTimeLocal": "17:00:00",
      "strGroup": null,
      "idHomeTeam": "133937",
      "strHomeTeamBadge": null,
      "idAwayTeam": "133734",
      "strAwayTeamBadge": null,
      "intScore": null,
      "intScoreVotes": null,
      "strResult": "",
      "idVenue": "19057",
      "strVenue": "Abanca-Balaídos",
      "strCountry": "Spain",
      "strCity": "",
      "strPoster": "",
      "strSquare": "https://r2.thesportsdb.com/images/media/event/square/yb0w5j1661600194.jpg",
      "strFanart": null,
      "strThumb": "https://r2.thesportsdb.com/images/media/event/thumb/6ojdpw1661596855.jpg",
      "strBanner": "",
      "strMap": null,
      "strTweet1": "",
      "strVideo": "https://www.youtube.com/watch?v=eiEXiGmo4o4",
      "strStatus": "Match Finished",
      "strPostponed": "no",
      "strLocked": "unlocked"
    },
    {
      "idEvent": "1580274",
      "idAPIfootball": "877950",
      "strTimestamp": "2022-08-13T18:00:00",
      "strEvent": "Valladolid vs Villarreal",
      "strEventAlternate": "Villarreal @ Valladolid",
      "strFilename": "Spanish La Liga 2022-08-13 Valladolid vs Villarreal",
      "strSport": "Soccer",
      "idLeague": "4335",
      "strLeague": "Spanish La Liga",
      "strLeagueBadge": "https://r2.thesportsdb.com/images/media/league/badge/ja4it51687628717.png",
      "strSeason": "2022-2023",
      "strDescriptionEN": "After only one year of absence, the Valladolid of the \"Phenomenon\" Ronaldo returns to the Liga and does so in front of their fans, at the Estadio Municipal José Zorrilla. Against them there is Villarreal, protagonist of a surprising season, culminating in a Champions League semi-final.",
      "strHomeTeam": "Valladolid",
      "strAwayTeam": "Villarreal",
      "intHomeScore": "0",
      "intRound": "1",
      "intAwayScore": "3",
      "intSpectators": null,
      "strOfficial": "",
      "dateEvent": "2022-08-13",
      "dateEventLocal": "2022-08-13",
      "strTime": "17:00:00",
      "strTimeLocal": "19:00:00",
      "strGroup": null,
      "idHomeTeam": "133841",
      "strHomeTeamBadge": null,
      "idAwayTeam": "133740",
      "strAwayTeamBadge": null,
      "intScore": null,
      "intScoreVotes": null,
      "strResult": "",
      "idVenue": "18355",
      "strVenue": "Estadio Municipal José Zorrilla",
      "strCountry": "Spain",
      "strCity": "",
      "strPoster": "",
      "strSquare": "https://r2.thesportsdb.com/images/media/event/square/mdwqzv1661600196.jpg",
      "strFanart": null,
      "strThumb": "https://r2.thesportsdb.com/images/media/event/thumb/f6t9gi1661596857.jpg",
      "strBanner": "",
      "strMap": null,
      "strTweet1": "",
      "strVideo": "https://www.youtube.com/watch?v=G5fKDU7PjoQ",
      "strStatus": "Match Finished",
      "strPostponed": "no",
      "strLocked": "unlocked"
    },
    {
      "idEvent": "1580270",
      "idAPIfootball": "877946",
      "strTimestamp": "2022-08-14T16:30:00",
      "strEvent": "Cadiz vs Sociedad",
      "strEventAlternate": "Sociedad @ Cadiz",
      "strFilename": "Spanish La Liga 2022-08-14 Cadiz vs Sociedad",
      "strSport": "Soccer",
      "idLeague": "4335",
      "strLeague": "Spanish La Liga",
      "strLeagueBadge": "https://r2.thesportsdb.com/images/media/league/badge/ja4it51687628717.png",
      "strSeason": "2022-2023",
      "strDescriptionEN": "After the salvation achieved on the last day of last season, Sergio González’s Cadiz begins their third consecutive season in La Liga. Real Sociedad is the opponent of the debut at the Nuevo Mirandilla, ready to live another season fighting for Europe.",
      "strHomeTeam": "Cadiz",
      "strAwayTeam": "Sociedad",
      "intHomeScore": "0",
      "intRound": "1",
      "intAwayScore": "1",
      "intSpectators": null,
      "strOfficial": "",
      "dateEvent": "2022-08-14",
      "dateEventLocal": "2022-08-14",
      "strTime": "15:30:00",
      "strTimeLocal": "17:30:00",
      "strGroup": null,
      "idHomeTeam": "134222",
      "strHomeTeamBadge": null,
      "idAwayTeam": "133724",
      "strAwayTeamBadge": null,
      "intScore": null,
      "intScoreVotes": null,
      "strResult": "",
      "idVenue": "21691",
      "strVenue": "Estadio Nuevo Mirandilla",
      "strCountry": "Spain",
      "strCity": "",
      "strPoster": "",
      "strSquare": "https://r2.thesportsdb.com/images/media/event/square/q0t0581661600194.jpg",
      "strFanart": null,
      "strThumb": "https://r2.thesportsdb.com/images/media/event/thumb/o14wcy1661596855.jpg",
      "strBanner": "",
      "strMap": null,
      "strTweet1": "",
      "strVideo": "https://www.youtube.com/watch?v=3TLiBMF7GTs",
      "strStatus": "Match Finished",
      "strPostponed": "no",
      "strLocked": "unlocked"
    },
    {
      "idEvent": "1580272",
      "idAPIfootball": "877948",
      "strTimestamp": "2022-08-14T21:00:00",
      "strEvent": "Almeria vs Real Madrid",
      "strEventAlternate": "Real Madrid @ Almeria",
      "strFilename": "Spanish La Liga 2022-08-14 Almeria vs Real Madrid",
      "strSport": "Soccer",
      "idLeague": "4335",
      "strLeague": "Spanish La Liga",
      "strLeagueBadge": "https://r2.thesportsdb.com/images/media/league/badge/ja4it51687628717.png",
      "strSeason": "2022-2023",
      "strDescriptionEN": "Having disposed of the summer holidays and the preparation, the championship in Spain finally starts again. After 7 years of waiting, Almeria returns to the Primera División and the departure immediately proposes the biggest obstacle to overcome: the Real Madrid of Carlo Ancelotti, reigning Liga and Champions League champions.",
      "strHomeTeam": "Almeria",
      "strAwayTeam": "Real Madrid",
      "intHomeScore": "1",
      "intRound": "1",
      "intAwayScore": "2",
      "intSpectators": null,
      "strOfficial": "",
      "dateEvent": "2022-08-14",
      "dateEventLocal": "2022-08-14",
      "strTime": "20:00:00",
      "strTimeLocal": "22:00:00",
      "strGroup": null,
      "idHomeTeam": "133817",
      "strHomeTeamBadge": null,
      "idAwayTeam": "133738",
      "strAwayTeamBadge": null,
      "intScore": null,
      "intScoreVotes": null,
      "strResult": "",
      "idVenue": null,
      "strVenue": "Power Horse Stadium – Estadio de los Juegos Mediterráneos",
      "strCountry": "Spain",
      "strCity": "",
      "strPoster": "",
      "strSquare": "https://r2.thesportsdb.com/images/media/event/square/wbacla1661600195.jpg",
      "strFanart": null,
      "strThumb": "https://r2.thesportsdb.com/images/media/event/thumb/afybfu1661596856.jpg",
      "strBanner": "",
      "strMap": null,
      "strTweet1": "",
      "strVideo": "https://www.youtube.com/watch?v=I-dGUYSnTU8",
      "strStatus": "Match Finished",
      "strPostponed": "no",
      "strLocked": "unlocked"
    },
    {
      "idEvent": "1580275",
      "idAPIfootball": "877951",
      "strTimestamp": "2022-08-14T18:30:00",
      "strEvent": "Valencia vs Girona",
      "strEventAlternate": "Girona @ Valencia",
      "strFilename": "Spanish La Liga 2022-08-14 Valencia vs Girona",
      "strSport": "Soccer",
      "idLeague": "4335",
      "strLeague": "Spanish La Liga",
      "strLeagueBadge": "https://r2.thesportsdb.com/images/media/league/badge/ja4it51687628717.png",
      "strSeason": "2022-2023",
      "strDescriptionEN": "Mestalla receives Girona FC's return to the category on the first date of the championship, two seasons later. The people from Girona make their First Division debut against Gattuso's team, who makes his debut as coach in LaLiga in Spain after passing through the benches in Switzerland, Greece and Italy.",
      "strHomeTeam": "Valencia",
      "strAwayTeam": "Girona",
      "intHomeScore": "1",
      "intRound": "1",
      "intAwayScore": "0",
      "intSpectators": null,
      "strOfficial": "",
      "dateEvent": "2022-08-14",
      "dateEventLocal": "2022-08-14",
      "strTime": "17:30:00",
      "strTimeLocal": "19:30:00",
      "strGroup": null,
      "idHomeTeam": "133725",
      "strHomeTeamBadge": null,
      "idAwayTeam": "134700",
      "strAwayTeamBadge": null,
      "intScore": null,
      "intScoreVotes": null,
      "strResult": "",
      "idVenue": "19054",
      "strVenue": "Estadio de Mestalla",
      "strCountry": "Spain",
      "strCity": "",
      "strPoster": "",
      "strSquare": "https://r2.thesportsdb.com/images/media/event/square/jmhp771661600196.jpg",
      "strFanart": null,
      "strThumb": "https://r2.thesportsdb.com/images/media/event/thumb/j8464o1661596858.jpg",
      "strBanner": "",
      "strMap": null,
      "strTweet1": "",
      "strVideo": "https://www.youtube.com/watch?v=IveDcHrfv0Q",
      "strStatus": "Match Finished",
      "strPostponed": "no",
      "strLocked": "unlocked"
    },
    {
      "idEvent": "1580266",
      "idAPIfootball": "877942",
      "strTimestamp": "2022-08-15T16:30:00",
      "strEvent": "Ath Bilbao vs Mallorca",
      "strEventAlternate": "Mallorca @ Ath Bilbao",
      "strFilename": "Spanish La Liga 2022-08-15 Ath Bilbao vs Mallorca",
      "strSport": "Soccer",
      "idLeague": "4335",
      "strLeague": "Spanish La Liga",
      "strLeagueBadge": "https://r2.thesportsdb.com/images/media/league/badge/ja4it51687628717.png",
      "strSeason": "2022-2023",
      "strDescriptionEN": "San Mamés opens its doors to LaLiga 2022/23 with an old acquaintance on its bench. Ernesto Valverde begins his third stage as head coach at Athletic Club and with the dream of returning the team to Europe. Opposite will be Mallorca, which lands in Bilbao captained by El Vasco Aguirre, the coach who arrived at the end of last season to save the team and fulfilled his mission. He now has the opportunity to start a course from scratch and prevent the vermilion from suffering to stay in the First Division.",
      "strHomeTeam": "Ath Bilbao",
      "strAwayTeam": "Mallorca",
      "intHomeScore": "0",
      "intRound": "1",
      "intAwayScore": "0",
      "intSpectators": null,
      "strOfficial": "",
      "dateEvent": "2022-08-15",
      "dateEventLocal": "2022-08-15",
      "strTime": "15:30:00",
      "strTimeLocal": "17:30:00",
      "strGroup": null,
      "idHomeTeam": "133727",
      "strHomeTeamBadge": null,
      "idAwayTeam": "133733",
      "strAwayTeamBadge": null,
      "intScore": null,
      "intScoreVotes": null,
      "strResult": "",
      "idVenue": "16468",
      "strVenue": "San Mamés Barria",
      "strCountry": "Spain",
      "strCity": "",
      "strPoster": "",
      "strSquare": "https://r2.thesportsdb.com/images/media/event/square/l05vkg1661600192.jpg",
      "strFanart": null,
      "strThumb": "https://r2.thesportsdb.com/images/media/event/thumb/hk8grk1661596853.jpg",
      "strBanner": "",
      "strMap": null,
      "strTweet1": "",
      "strVideo": "https://www.youtube.com/watch?v=ik7XnSgbttM",
      "strStatus": "Match Finished",
      "strPostponed": "no",
      "strLocked": "unlocked"
    },
    {
      "idEvent": "1580268",
      "idAPIfootball": "877944",
      "strTimestamp": "2022-08-15T20:30:00",
      "strEvent": "Betis vs Elche",
      "strEventAlternate": "Elche @ Betis",
      "strFilename": "Spanish La Liga 2022-08-15 Betis vs Elche",
      "strSport": "Soccer",
      "idLeague": "4335",
      "strLeague": "Spanish La Liga",
      "strLeagueBadge": "https://r2.thesportsdb.com/images/media/league/badge/ja4it51687628717.png",
      "strSeason": "2022-2023",
      "strDescriptionEN": "Elche's third consecutive season in the First Division, which is the club's best run in the elite this century. The people from Elche start the season in a stadium where they won on their last visit. Real Betis, for its part, current champion of the Cup, and European team for this season, is in luck for signing more than 50 courses in the elite.",
      "strHomeTeam": "Betis",
      "strAwayTeam": "Elche",
      "intHomeScore": "3",
      "intRound": "1",
      "intAwayScore": "0",
      "intSpectators": null,
      "strOfficial": "",
      "dateEvent": "2022-08-15",
      "dateEventLocal": "2022-08-15",
      "strTime": "19:30:00",
      "strTimeLocal": "21:30:00",
      "strGroup": null,
      "idHomeTeam": "133722",
      "strHomeTeamBadge": null,
      "idAwayTeam": "134384",
      "strAwayTeamBadge": null,
      "intScore": null,
      "intScoreVotes": null,
      "strResult": "",
      "idVenue": "19056",
      "strVenue": "Estadio Benito Villamarín",
      "strCountry": "Spain",
      "strCity": "",
      "strPoster": "",
      "strSquare": "https://r2.thesportsdb.com/images/media/event/square/rs4ms31661600193.jpg",
      "strFanart": null,
      "strThumb": "https://r2.thesportsdb.com/images/media/event/thumb/db6mjn1661596854.jpg",
      "strBanner": "",
      "strMap": null,
      "strTweet1": "",
      "strVideo": "https://www.youtube.com/watch?v=zEqnNvM9gvk",
      "strStatus": "Match Finished",
      "strPostponed": "no",
      "strLocked": "unlocked"
    },
    {
      "idEvent": "1580273",
      "idAPIfootball": "877949",
      "strTimestamp": "2022-08-15T18:30:00",
      "strEvent": "Getafe vs Ath Madrid",
      "strEventAlternate": "Ath Madrid @ Getafe",
      "strFilename": "Spanish La Liga 2022-08-15 Getafe vs Ath Madrid",
      "strSport": "Soccer",
      "idLeague": "4335",
      "strLeague": "Spanish La Liga",
      "strLeagueBadge": "https://r2.thesportsdb.com/images/media/league/badge/ja4it51687628717.png",
      "strSeason": "2022-2023",
      "strDescriptionEN": "With the Madrid derby between Getafe and Atletico, the twelfth season of Diego Simeone on the bench of the \"Colchoneros\" kicks off. In the last championship the \"Cholo\" team won both the first leg and the return leg with two hard-earned but deserved victories: the 4-3 comeback at the Wanda Metropolitano is emblematic.",
      "strHomeTeam": "Getafe",
      "strAwayTeam": "Ath Madrid",
      "intHomeScore": "0",
      "intRound": "1",
      "intAwayScore": "3",
      "intSpectators": null,
      "strOfficial": "",
      "dateEvent": "2022-08-15",
      "dateEventLocal": "2022-08-15",
      "strTime": "17:30:00",
      "strTimeLocal": "19:30:00",
      "strGroup": null,
      "idHomeTeam": "133731",
      "strHomeTeamBadge": null,
      "idAwayTeam": "133729",
      "strAwayTeamBadge": null,
      "intScore": null,
      "intScoreVotes": null,
      "strResult": "",
      "idVenue": null,
      "strVenue": "Coliseum Alfonso Pérez",
      "strCountry": "Spain",
      "strCity": "",
      "strPoster": "",
      "strSquare": "https://r2.thesportsdb.com/images/media/event/square/u4cpsi1661600196.jpg",
      "strFanart": null,
      "strThumb": "https://r2.thesportsdb.com/images/media/event/thumb/y1rt0u1661596857.jpg",
      "strBanner": "",
      "strMap": null,
      "strTweet1": "",
      "strVideo": "https://www.youtube.com/watch?v=QfYLwiB6RjE",
      "strStatus": "Match Finished",
      "strPostponed": "no",
      "strLocked": "unlocked"
    },
    {
      "idEvent": "1580279",
      "idAPIfootball": "877955",
      "strTimestamp": "2022-08-19T19:00:00",
      "strEvent": "Espanol vs Vallecano",
      "strEventAlternate": "Vallecano @ Espanol",
      "strFilename": "Spanish La Liga 2022-08-19 Espanol vs Vallecano",
      "strSport": "Soccer",
      "idLeague": "4335",
      "strLeague": "Spanish La Liga",
      "strLeagueBadge": "https://r2.thesportsdb.com/images/media/league/badge/ja4it51687628717.png",
      "strSeason": "2022-2023",
      "strDescriptionEN": "Vicente Moreno's Espanyol is looking for a rematch after Rayo Vallecano's two defeats last year, both 1-0. In the previous twenty in which the two clubs have been involved, however, absolute parity reigns: eight wins each and four draws, but the Periquitos of Barcelona will try to reverse the trend and move forward in the dispute against Madrid opponents.",
      "strHomeTeam": "Espanol",
      "strAwayTeam": "Vallecano",
      "intHomeScore": "0",
      "intRound": "2",
      "intAwayScore": "2",
      "intSpectators": null,
      "strOfficial": "",
      "dateEvent": "2022-08-19",
      "dateEventLocal": "2022-08-19",
      "strTime": "18:00:00",
      "strTimeLocal": "20:00:00",
      "strGroup": null,
      "idHomeTeam": "133734",
      "strHomeTeamBadge": null,
      "idAwayTeam": "133728",
      "strAwayTeamBadge": null,
      "intScore": null,
      "intScoreVotes": null,
      "strResult": "",
      "idVenue": "19361",
      "strVenue": "RCDE Stadium",
      "strCountry": "Spain",
      "strCity": "",
      "strPoster": "",
      "strSquare": "https://r2.thesportsdb.com/images/media/event/square/96lv5j1661600199.jpg",
      "strFanart": null,
      "strThumb": "https://r2.thesportsdb.com/images/media/event/thumb/t8ixxs1661596860.jpg",
      "strBanner": "",
      "strMap": null,
      "strTweet1": "",
      "strVideo": "https://www.youtube.com/watch?v=Moj1bS2nO2Y",
      "strStatus": "Match Finished",
      "strPostponed": "no",
      "strLocked": "unlocked"
    },
    {
      "idEvent": "1580280",
      "idAPIfootball": "877956",
      "strTimestamp": "2022-08-19T21:00:00",
      "strEvent": "Sevilla vs Valladolid",
      "strEventAlternate": "Valladolid @ Sevilla",
      "strFilename": "Spanish La Liga 2022-08-19 Sevilla vs Valladolid",
      "strSport": "Soccer",
      "idLeague": "4335",
      "strLeague": "Spanish La Liga",
      "strLeagueBadge": "https://r2.thesportsdb.com/images/media/league/badge/ja4it51687628717.png",
      "strSeason": "2022-2023",
      "strDescriptionEN": "Lopetegui's Sevilla make their debut within the walls of Ramon Sanchez Pizjuan against newly promoted Valladolid, who two years ago managed to come out unscathed from both duels by snatching a draw, both first leg and return. The team owned by the Phenomenon Ronaldo has not won against the Andalusians for ten years: is it time for the company?",
      "strHomeTeam": "Sevilla",
      "strAwayTeam": "Valladolid",
      "intHomeScore": "1",
      "intRound": "2",
      "intAwayScore": "1",
      "intSpectators": null,
      "strOfficial": "",
      "dateEvent": "2022-08-19",
      "dateEventLocal": "2022-08-19",
      "strTime": "20:00:00",
      "strTimeLocal": "22:00:00",
      "strGroup": null,
      "idHomeTeam": "133735",
      "strHomeTeamBadge": null,
      "idAwayTeam": "133841",
      "strAwayTeamBadge": null,
      "intScore": null,
      "intScoreVotes": null,
      "strResult": "",
      "idVenue": "18689",
      "strVenue": "Estadio Ramón Sánchez Pizjuán",
      "strCountry": "Spain",
      "strCity": "",
      "strPoster": "",
      "strSquare": "https://r2.thesportsdb.com/images/media/event/square/7yxyu11661600200.jpg",
      "strFanart": null,
      "strThumb": "https://r2.thesportsdb.com/images/media/event/thumb/4lsv8y1661596860.jpg",
      "strBanner": "",
      "strMap": null,
      "strTweet1": "",
      "strVideo": "https://www.youtube.com/watch?v=QJIjRbCGPJI",
      "strStatus": "Match Finished",
      "strPostponed": "no",
      "strLocked": "unlocked"
    },
    {
      "idEvent": "1580284",
      "idAPIfootball": "877960",
      "strTimestamp": "2022-08-20T16:30:00",
      "strEvent": "Osasuna vs Cadiz",
      "strEventAlternate": "Cadiz @ Osasuna",
      "strFilename": "Spanish La Liga 2022-08-20 Osasuna vs Cadiz",
      "strSport": "Soccer",
      "idLeague": "4335",
      "strLeague": "Spanish La Liga",
      "strLeagueBadge": "https://r2.thesportsdb.com/images/media/league/badge/ja4it51687628717.png",
      "strSeason": "2022-2023",
      "strDescriptionEN": "Osasuna is playing its second consecutive game at El Sadar at this start of LaLiga. Jagoba Arrasate's rojillos host Sergio González's Cádiz in a north-south duel that ended with two victories for the Navarrese last season.",
      "strHomeTeam": "Osasuna",
      "strAwayTeam": "Cadiz",
      "intHomeScore": "2",
      "intRound": "2",
      "intAwayScore": "0",
      "intSpectators": null,
      "strOfficial": "",
      "dateEvent": "2022-08-20",
      "dateEventLocal": "2022-08-20",
      "strTime": "15:30:00",
      "strTimeLocal": "17:30:00",
      "strGroup": null,
      "idHomeTeam": "133730",
      "strHomeTeamBadge": null,
      "idAwayTeam": "134222",
      "strAwayTeamBadge": null,
      "intScore": null,
      "intScoreVotes": null,
      "strResult": "",
      "idVenue": "19060",
      "strVenue": "Estadio El Sadar",
      "strCountry": "Spain",
      "strCity": "",
      "strPoster": "",
      "strSquare": "https://r2.thesportsdb.com/images/media/event/square/v3t8za1661600203.jpg",
      "strFanart": null,
      "strThumb": "https://r2.thesportsdb.com/images/media/event/thumb/gq1es11661596862.jpg",
      "strBanner": "",
      "strMap": null,
      "strTweet1": "",
      "strVideo": "https://www.youtube.com/watch?v=IqHwppvSAOs",
      "strStatus": "Match Finished",
      "strPostponed": "no",
      "strLocked": "unlocked"
    },
    {
      "idEvent": "1580278",
      "idAPIfootball": "877954",
      "strTimestamp": "2022-08-20T21:00:00",
      "strEvent": "Celta Vigo vs Real Madrid",
      "strEventAlternate": "Real Madrid @ Celta Vigo",
      "strFilename": "Spanish La Liga 2022-08-20 Celta Vigo vs Real Madrid",
      "strSport": "Soccer",
      "idLeague": "4335",
      "strLeague": "Spanish La Liga",
      "strLeagueBadge": "https://r2.thesportsdb.com/images/media/league/badge/ja4it51687628717.png",
      "strSeason": "2022-2023",
      "strDescriptionEN": "Vigo was traditionally a difficult place in the 20th century for Real Madrid, at the height of the Camp Nou. Whites, in this last decade and in this century, have changed this trend in Galicia. Not in vain, Celta has not beaten the meringues in Balaídos since 2014, with a double by Charles. Luis Enrique trained in the Olívico squad and Carlo Ancelotti was on the Madrid bench, during his previous stage at the Chamartín club.",
      "strHomeTeam": "Celta Vigo",
      "strAwayTeam": "Real Madrid",
      "intHomeScore": "1",
      "intRound": "2",
      "intAwayScore": "4",
      "intSpectators": null,
      "strOfficial": "",
      "dateEvent": "2022-08-20",
      "dateEventLocal": "2022-08-20",
      "strTime": "20:00:00",
      "strTimeLocal": "22:00:00",
      "strGroup": null,
      "idHomeTeam": "133937",
      "strHomeTeamBadge": null,
      "idAwayTeam": "133738",
      "strAwayTeamBadge": null,
      "intScore": null,
      "intScoreVotes": null,
      "strResult": "",
      "idVenue": "19057",
      "strVenue": "Abanca-Balaídos",
      "strCountry": "Spain",
      "strCity": "",
      "strPoster": "",
      "strSquare": "https://r2.thesportsdb.com/images/media/event/square/ga8cr61661600198.jpg",
      "strFanart": null,
      "strThumb": "https://r2.thesportsdb.com/images/media/event/thumb/gqj2bf1661596859.jpg",
      "strBanner": "",
      "strMap": null,
      "strTweet1": "",
      "strVideo": "https://www.youtube.com/watch?v=uY9QGh5BfQM",
      "strStatus": "Match Finished",
      "strPostponed": "no",
      "strLocked": "unlocked"
    },
    {
      "idEvent": "1580282",
      "idAPIfootball": "877958",
      "strTimestamp": "2022-08-20T18:30:00",
      "strEvent": "Mallorca vs Betis",
      "strEventAlternate": "Betis @ Mallorca",
      "strFilename": "Spanish La Liga 2022-08-20 Mallorca vs Betis",
      "strSport": "Soccer",
      "idLeague": "4335",
      "strLeague": "Spanish La Liga",
      "strLeagueBadge": "https://r2.thesportsdb.com/images/media/league/badge/ja4it51687628717.png",
      "strSeason": "2022-2023",
      "strDescriptionEN": "Transfer to the Balearics for Pellegrini's Betis in this second round of the championship. Waiting for them at Iberostar is the Maiorca dellex Lazio Muriqi, ready and loaded to put their name on the match report.",
      "strHomeTeam": "Mallorca",
      "strAwayTeam": "Betis",
      "intHomeScore": "1",
      "intRound": "2",
      "intAwayScore": "2",
      "intSpectators": null,
      "strOfficial": "",
      "dateEvent": "2022-08-20",
      "dateEventLocal": "2022-08-20",
      "strTime": "17:30:00",
      "strTimeLocal": "19:30:00",
      "strGroup": null,
      "idHomeTeam": "133733",
      "strHomeTeamBadge": null,
      "idAwayTeam": "133722",
      "strAwayTeamBadge": null,
      "intScore": null,
      "intScoreVotes": null,
      "strResult": "",
      "idVenue": "21692",
      "strVenue": "Visit Mallorca Estadi",
      "strCountry": "Spain",
      "strCity": "",
      "strPoster": "",
      "strSquare": "https://r2.thesportsdb.com/images/media/event/square/3eg59q1661600201.jpg",
      "strFanart": null,
      "strThumb": "https://r2.thesportsdb.com/images/media/event/thumb/yjvcc81661596861.jpg",
      "strBanner": "",
      "strMap": null,
      "strTweet1": "",
      "strVideo": "https://www.youtube.com/watch?v=wpom4IBhQKo",
      "strStatus": "Match Finished",
      "strPostponed": "no",
      "strLocked": "unlocked"
    }
  ]
}